pyAntiSSRF/__init__.py
pyAntiSSRF/utils/__init__.py
pyAntiSSRF/utils/compat.py
pyAntiSSRF/utils/helper.py
pyAntiSSRF-0.0.3.dist-info/LICENSE
pyAntiSSRF-0.0.3.dist-info/MANiFEST.in
pyAntiSSRF-0.0.3.dist-info/METADATA
pyAntiSSRF-0.0.3.dist-info/WHEEL
pyAntiSSRF-0.0.3.dist-info/top_level.txt
pyAntiSSRF-0.0.3.dist-info/RECORD
