Metadata-Version: 2.1
Name: pyAntiSSRF
Version: 0.0.3
Summary: python anti ssrf by hijack requests
Home-page: https://github.com/yangbh/pyAntiSSRF
Author: m0d9
Author-email: 0xyangbh@gmail.com
License: BSD License
Platform: all
Requires-Dist: requests
